django_dramatiq/__init__.py
django_dramatiq/admin.py
django_dramatiq/apps.py
django_dramatiq/middleware.py
django_dramatiq/models.py
django_dramatiq/setup.py
django_dramatiq/tasks.py
django_dramatiq/test.py
django_dramatiq/utils.py
django_dramatiq/management/__init__.py
django_dramatiq/management/commands/__init__.py
django_dramatiq/management/commands/rundramatiq.py
django_dramatiq/migrations/0001_initial.py
django_dramatiq/migrations/0002_auto_20191104_1354.py
django_dramatiq/migrations/0003_auto_20200204_0842.py
django_dramatiq/migrations/__init__.py
django_dramatiq-0.14.0.dist-info/licenses/LICENSE
django_dramatiq-0.14.0.dist-info/METADATA
django_dramatiq-0.14.0.dist-info/WHEEL
django_dramatiq-0.14.0.dist-info/top_level.txt
django_dramatiq-0.14.0.dist-info/RECORD
